lib/__init__.py
lib/integracije.py
integracije-0.0.1.dist-info/LICENCE.md
integracije-0.0.1.dist-info/METADATA
integracije-0.0.1.dist-info/WHEEL
integracije-0.0.1.dist-info/top_level.txt
integracije-0.0.1.dist-info/RECORD
