Metadata-Version: 2.1
Name: integracije
Version: 0.0.1
Summary: Paket za izris grafa aplikacije in vmesnikov.
Home-page: UNKNOWN
Author: Hana Balan
Author-email: <hana.balan@student.um.si>
License: UNKNOWN
Platform: UNKNOWN
Classifier: Development Status :: 1 - Planning
Classifier: Programming Language :: Python :: 3
Classifier: Operating System :: OS Independent
License-File: LICENCE.md
Requires-Dist: pandas
Requires-Dist: graphviz
